sentier_peakachu/__init__.py
sentier_peakachu/data.py
sentier_peakachu/entsoe.py
sentier_peakachu/iri_mapping.py
sentier_peakachu/model.py
sentier_peakachu/utils_location.py
sentier_peakachu/utils_time.py
sentier_peakachu-0.2.1.dist-info/LICENSE
sentier_peakachu-0.2.1.dist-info/METADATA
sentier_peakachu-0.2.1.dist-info/WHEEL
sentier_peakachu-0.2.1.dist-info/top_level.txt
sentier_peakachu-0.2.1.dist-info/RECORD
