Metadata-Version: 2.1
Name: sentier_peakachu
Version: 0.2.1
Summary: Modeling electricity stuff
Author-email: Timo Diepers <timo.diepers@ltt.rwth-aachen.de>
Maintainer-email: Timo Diepers <timo.diepers@ltt.rwth-aachen.de>
Project-URL: source, https://github.com/TimoDiepers/sentier_peakachu
Project-URL: homepage, https://github.com/TimoDiepers/sentier_peakachu
Project-URL: tracker, https://github.com/TimoDiepers/sentier_peakachu/issues
Classifier: Development Status :: 4 - Beta
Classifier: Programming Language :: Python
Classifier: Programming Language :: Python :: 3
Classifier: Programming Language :: Python :: 3.11
Classifier: Programming Language :: Python :: 3.12
Classifier: Natural Language :: English
Classifier: Operating System :: OS Independent
Classifier: Topic :: Scientific/Engineering
Requires-Python: >=3.11
License-File: LICENSE
Requires-Dist: python-dotenv
Requires-Dist: entsoe-py
Requires-Dist: sentier-data-tools
Requires-Dist: loguru
Requires-Dist: polars
Provides-Extra: dev
Requires-Dist: build ; extra == 'dev'
Requires-Dist: pre-commit ; extra == 'dev'
Requires-Dist: pylint ; extra == 'dev'
Requires-Dist: pytest ; extra == 'dev'
Requires-Dist: pytest-cov ; extra == 'dev'
Requires-Dist: pytest-randomly ; extra == 'dev'
Requires-Dist: setuptools ; extra == 'dev'
Provides-Extra: testing
Requires-Dist: pytest ; extra == 'testing'
Requires-Dist: pytest-cov ; extra == 'testing'
Requires-Dist: python-coveralls ; extra == 'testing'
